README.md
setup.py
autocheckauctions/__init__.py
autocheckauctions/api_client.py
autocheckauctions/configuration.py
autocheckauctions/rest.py
autocheckauctions/api/__init__.py
autocheckauctions/api/batch_api.py
autocheckauctions/api/default_api.py
autocheckauctions/api/vehicle_api.py
autocheckauctions/api/vehicle_history_api.py
autocheckauctions/models/__init__.py
autocheckauctions/models/batch_report_response.py
autocheckauctions/models/batch_request.py
autocheckauctions/models/batch_response.py
autocheckauctions/models/empty.py
autocheckauctions/models/history_record.py
autocheckauctions/models/history_request.py
autocheckauctions/models/history_response.py
autocheckauctions/models/recall_record.py
autocheckauctions/models/unprocessed_history_requests.py
autocheckauctions/models/vehicle.py
autocheckauctions/models/vehicle_announcement.py
autocheckauctions/models/vehicle_history.py
autocheckauctions/models/vehicle_information.py
autocheckauctions/models/vehicle_ownership_activity.py
autocheckauctions/models/vehicle_recall.py
autocheckauctions/models/vehicle_request_attribute.py
autocheckauctions/models/vehicle_scoring.py
autocheckauctions_api_python_client.egg-info/PKG-INFO
autocheckauctions_api_python_client.egg-info/SOURCES.txt
autocheckauctions_api_python_client.egg-info/dependency_links.txt
autocheckauctions_api_python_client.egg-info/requires.txt
autocheckauctions_api_python_client.egg-info/top_level.txt
test/__init__.py
test/test_batch_api.py
test/test_batch_report_response.py
test/test_batch_request.py
test/test_batch_response.py
test/test_default_api.py
test/test_empty.py
test/test_history_record.py
test/test_history_request.py
test/test_history_response.py
test/test_recall_record.py
test/test_unprocessed_history_requests.py
test/test_vehicle.py
test/test_vehicle_announcement.py
test/test_vehicle_api.py
test/test_vehicle_history.py
test/test_vehicle_history_api.py
test/test_vehicle_information.py
test/test_vehicle_ownership_activity.py
test/test_vehicle_recall.py
test/test_vehicle_request_attribute.py
test/test_vehicle_scoring.py