Metadata-Version: 1.0
Name: autocheckauctions-api-python-client
Version: 1.4.3
Summary: ACA Services API
Home-page: UNKNOWN
Author: UNKNOWN
Author-email: UNKNOWN
License: UNKNOWN
Keywords: Swagger,ACA Services API
Platform: UNKNOWN
